pyshbundle/GRACE_Data_Driven_Correction_Vishwakarma.py
pyshbundle/GRACEconstants.py
pyshbundle/GRACEpy.py
pyshbundle/Phase_calc.py
pyshbundle/__init__.py
pyshbundle/basin_avg.py
pyshbundle/clm2cs.py
pyshbundle/clm2sc.py
pyshbundle/conv_sh.py
pyshbundle/cs2sc.py
pyshbundle/eigengrav.py
pyshbundle/gaussian.py
pyshbundle/grule.py
pyshbundle/gsha.py
pyshbundle/gshs.py
pyshbundle/hydro.py
pyshbundle/io.py
pyshbundle/iplm.py
pyshbundle/ispec.py
pyshbundle/klm2sc.py
pyshbundle/load_longterm_mean.py
pyshbundle/naninterp.py
pyshbundle/neumann.py
pyshbundle/new_io.py
pyshbundle/normalklm.py
pyshbundle/plm.py
pyshbundle/pysh_core.py
pyshbundle/pyshbundle.py
pyshbundle/read_GRACE_SH_paths.py
pyshbundle/reader_replacer.py
pyshbundle/reader_replacer_csr.py
pyshbundle/reader_replacer_itsg.py
pyshbundle/reader_replacer_jpl.py
pyshbundle/sc2cs.py
pyshbundle/shutils.py
pyshbundle/tws_cal.py
pyshbundle/viz_utils.py
pyshbundle-1.0.0.dist-info/LICENSE
pyshbundle-1.0.0.dist-info/METADATA
pyshbundle-1.0.0.dist-info/WHEEL
pyshbundle-1.0.0.dist-info/dependency_links.txt
pyshbundle-1.0.0.dist-info/top_level.txt
pyshbundle-1.0.0.dist-info/RECORD
