Metadata-Version: 2.1
Name: pyshbundle
Version: 1.0.0
Summary: PySHbundle: A Python implementation of GRACE Spherical Harmonics Synthesis MATLAB codes SHbundle
Home-page: https://github.com/mn5hk/pyshbundle
Author: Amin Shakya
Author-email: aminshk50@gmail.com
License: GNU General Public License v3
Keywords: pyshbundle
Classifier: Development Status :: 2 - Pre-Alpha
Classifier: Intended Audience :: Developers
Classifier: License :: OSI Approved :: GNU General Public License v3 (GPLv3)
Classifier: Natural Language :: English
Classifier: Programming Language :: Python :: 3
Classifier: Programming Language :: Python :: 3.7
Classifier: Programming Language :: Python :: 3.8
Classifier: Programming Language :: Python :: 3.9
Classifier: Programming Language :: Python :: 3.10
Requires-Python: >=3.7
License-File: LICENSE
Requires-Dist: pip
Requires-Dist: grip
Requires-Dist: numpy
Requires-Dist: pandas
Requires-Dist: netCDF4
Requires-Dist: scipy
Requires-Dist: xarray
Requires-Dist: julian
Requires-Dist: geopandas
Requires-Dist: matplotlib
Requires-Dist: rasterio
Requires-Dist: shapely
Requires-Dist: tqdm
Requires-Dist: cartopy
Requires-Dist: ipykernel
Requires-Dist: jupyterlab
Requires-Dist: rioxarray
Requires-Dist: salem
